StreamlinedCryptography/__init__.py
StreamlinedCryptography/asym.py
StreamlinedCryptography/sym.py
StreamlinedCryptography/util/__init__.py
StreamlinedCryptography/util/enforce_types.py
StreamlinedCryptography/util/serialization.py
StreamlinedCryptography-1.0.0.dist-info/METADATA
StreamlinedCryptography-1.0.0.dist-info/WHEEL
StreamlinedCryptography-1.0.0.dist-info/top_level.txt
StreamlinedCryptography-1.0.0.dist-info/RECORD
