Metadata-Version: 2.1
Name: StreamlinedCryptography
Version: 1.0.0
Summary: A high-level cryptography library for symmetric and asymmetric operations.
Home-page: https://github.com/HaZeShade/StreamlinedCryptography
Author: Preston Coley
Author-email: prestoncoley0920@proton.me
License: MIT
Classifier: Programming Language :: Python :: 3
Classifier: License :: OSI Approved :: MIT License
Classifier: Operating System :: OS Independent
Requires-Python: >=3.12
Requires-Dist: cryptography >=42.0.7
